{"NMO1FssJxl7+KhAzjNLy2g==":"omg%20reno-96x80.png","zfl4TkFZrq/UvLXnydv8pg==":"mog-115x36.png","2Ix74Z0naB/bubc6LhKdAg==":"about2-v2-561x561.png","5snVvuI34Oq0/TRf6H66ZQ==":"about2-v2-1-561x561.png","z00Vysas56wHuK0r2xRAmg==":"1-1580x965.jpg","umV+scXmv1AT9XJ59PxhkA==":"about6-v2-561x561.png","Fjv1pghOqEweeaj9LJQCNQ==":"02_budget-friendly.svg","5lqA0Pm8N3pGoq0YIEV5gg==":"02_budget-friendly.png","SbhrO5uussmRV7prIf9Vww==":"dew-591x361.jpg","p/qC/+R4CAvRem8vYceBYg==":"zen-591x361.jpg","JJTmCaqcWsNaYEGuxzE+pA==":"1-591x361.jpg","K4ESsAW/6silUY0I2ogM9A==":"1%20(1)-591x361.jpg"}